Workbook

Sheet Paramètres
A1: PARAMÈTRES LÉGAUX - GUINÉE (CGI 2022)
A3: COTISATIONS CNSS
A4: Plancher CNSS: | B4: 550000
A5: Plafond CNSS: | B5: 2500000
A6: Taux salarié: | B6: 0.05
A7: Taux employeur: | B7: 0.18
A9: CHARGES PATRONALES
A10: Versement Forfaitaire (VF): | B10: 0.06
A11: Taxe Apprentissage (TA): | B11: 0.015
A13: BARÈME RTS (IRG) - CGI 2022
A14: Tranche | B14: De | C14: À | D14: Taux
A15: Tranche 1 | B15: 0 | C15: 1000000 | D15: 0
A16: Tranche 2 | B16: 1000001 | C16: 3000000 | D16: 0.05
A17: Tranche 3 | B17: 3000001 | C17: 5000000 | D17: 0.08
A18: Tranche 4 | B18: 5000001 | C18: 10000000 | D18: 0.1
A19: Tranche 5 | B19: 10000001 | C19: 20000000 | D19: 0.15
A20: Tranche 6 | B20: 20000001 | C20: Illimité | D20: 0.2

Sheet Saisie Salarié
A1: SAISIE DES DONNÉES SALARIÉ
A3: IDENTIFICATION
A4: Nom: | B4: DIALLO
A5: Prénom: | B5: Mamadou
A6: Matricule: | B6: EMP001
A7: Poste: | B7: Comptable Principal
A8: Mois/Année: | B8: Janvier 2026
A10: RÉMUNÉRATION
A11: Salaire de base: | B11: 2800000
A12: Prime de transport: | B12: 800000
A13: Prime de logement: | B13: 0
A14: Autres primes: | B14: 0
A16: RETENUES OPTIONNELLES
A17: Avance sur salaire: | B17: 160000
A18: Prêt (mensualité): | B18: 0
A19: Autres retenues: | B19: 0

Sheet Calcul Automatique
A1: CALCUL AUTOMATIQUE DE PAIE
A3: SALAIRE BRUT
A4: Salaire de base | B4: ='Saisie Salarié'!B11
A5: Prime transport | B5: ='Saisie Salarié'!B12
A6: Prime logement | B6: ='Saisie Salarié'!B13
A7: Autres primes | B7: ='Saisie Salarié'!B14
A8: TOTAL BRUT | B8: =SUM(B4:B7)
A10: COTISATION CNSS
A11: Assiette CNSS | B11: =MAX(MIN(B8,Paramètres!B5),Paramètres!B4) | C11: (plafonnée)
A12: CNSS Salarié (5%) | B12: =ROUND(B11*Paramètres!B6,0)
A13: CNSS Employeur (18%) | B13: =ROUND(B11*Paramètres!B7,0)
A15: IMPÔT SUR LE REVENU (IRG/RTS)
A16: Base imposable | B16: =B8-B12 | C16: (Brut - CNSS)
A17: Tranche 1 (0%) | B17: =IF(B16>1000000,0,0)
A18: Tranche 2 (5%) | B18: =IF(B16>1000000,ROUND(MIN(B16,3000000)-1000000,0)*0.05,0)
A19: Tranche 3 (8%) | B19: =IF(B16>3000000,ROUND(MIN(B16,5000000)-3000000,0)*0.08,0)
A20: Tranche 4 (10%) | B20: =IF(B16>5000000,ROUND(MIN(B16,10000000)-5000000,0)*0.1,0)
A21: Tranche 5 (15%) | B21: =IF(B16>10000000,ROUND(MIN(B16,20000000)-10000000,0)*0.15,0)
A22: Tranche 6 (20%) | B22: =IF(B16>20000000,ROUND(B16-20000000,0)*0.2,0)
A23: TOTAL IRG | B23: =SUM(B17:B22)
A25: TOTAL RETENUES
A26: CNSS Salarié | B26: =B12
A27: IRG | B27: =B23
A28: Avance sur salaire | B28: ='Saisie Salarié'!B17
A29: Prêt | B29: ='Saisie Salarié'!B18
A30: Autres retenues | B30: ='Saisie Salarié'!B19
A31: TOTAL RETENUES | B31: =SUM(B26:B30)
A33: NET À PAYER | B33: =B8-B31
A35: CHARGES PATRONALES
A36: CNSS Employeur (18%) | B36: =B13
A37: VF (6%) | B37: =ROUND(B8*Paramètres!B10,0)
A38: TA (1,5%) | B38: =ROUND(B8*Paramètres!B11,0)
A39: TOTAL CHARGES PATRONALES | B39: =SUM(B36:B38)
A41: COÛT TOTAL EMPLOYEUR | B41: =B8+B39

Sheet Comparaison
A1: COMPARAISON EXCEL vs APPLICATION
A3: Élément | B3: Excel | C3: Application | D3: Écart | E3: Statut
A4: Salaire brut | B4: ='Calcul Automatique'!B8 | C4: 0 | D4: =B4-C4 | E4: =IF(ABS(D4)<10,"✅ OK","❌ ÉCART")
A5: CNSS Salarié | B5: ='Calcul Automatique'!B12 | C5: 0 | D5: =B5-C5 | E5: =IF(ABS(D5)<10,"✅ OK","❌ ÉCART")
A6: IRG | B6: ='Calcul Automatique'!B23 | C6: 0 | D6: =B6-C6 | E6: =IF(ABS(D6)<10,"✅ OK","❌ ÉCART")
A7: Avance | B7: ='Calcul Automatique'!B28 | C7: 0 | D7: =B7-C7 | E7: =IF(ABS(D7)<10,"✅ OK","❌ ÉCART")
A8: Total retenues | B8: ='Calcul Automatique'!B31 | C8: 0 | D8: =B8-C8 | E8: =IF(ABS(D8)<10,"✅ OK","❌ ÉCART")
A9: Net à payer | B9: ='Calcul Automatique'!B33 | C9: 0 | D9: =B9-C9 | E9: =IF(ABS(D9)<10,"✅ OK","❌ ÉCART")
A10: CNSS Employeur | B10: ='Calcul Automatique'!B36 | C10: 0 | D10: =B10-C10 | E10: =IF(ABS(D10)<10,"✅ OK","❌ ÉCART")
A11: VF | B11: ='Calcul Automatique'!B37 | C11: 0 | D11: =B11-C11 | E11: =IF(ABS(D11)<10,"✅ OK","❌ ÉCART")
A12: TA | B12: ='Calcul Automatique'!B38 | C12: 0 | D12: =B12-C12 | E12: =IF(ABS(D12)<10,"✅ OK","❌ ÉCART")
A13: Total charges patronales | B13: ='Calcul Automatique'!B39 | C13: 0 | D13: =B13-C13 | E13: =IF(ABS(D13)<10,"✅ OK","❌ ÉCART")
A16: RÉSULTAT GLOBAL | B16: =IF(COUNTIF(E4:E13,"❌ ÉCART")=0,"✅ TOUS LES CALCULS SONT CORRECTS","❌ DES ÉCARTS ONT ÉTÉ DÉTECTÉS")
A18: INSTRUCTIONS:
A19: 1. Saisir les données du salarié dans l'onglet 'Saisie Salarié'
A20: 2. Reporter les valeurs de l'application dans la colonne 'Application' (C)
A21: 3. Vérifier que tous les statuts affichent '✅ OK'
A22: 4. En cas d'écart > 10 GNF, investiguer la différence
